collabllm/__init__.py
collabllm/metric.py
collabllm/reward.py
collabllm/simulation.py
collabllm/synthetic.py
collabllm/datasets/__init__.py
collabllm/datasets/multiturn.py
collabllm/datasets/single_turn.py
collabllm/modules/__init__.py
collabllm/modules/llm_collaborator.py
collabllm/modules/user_simulator.py
collabllm/prompts/__init__.py
collabllm/prompts/extract_multiturn_completion.txt
collabllm/prompts/proact_instruction.txt
collabllm/prompts/system_prompt.txt
collabllm/prompts/user_simulator.txt
collabllm/utils/extract_json_reliable.py
collabllm/utils/format.py
collabllm/utils/template.py
collabllm-0.0.8.dist-info/licenses/LICENSE
collabllm-0.0.8.dist-info/METADATA
collabllm-0.0.8.dist-info/WHEEL
collabllm-0.0.8.dist-info/top_level.txt
collabllm-0.0.8.dist-info/RECORD
