Metadata-Version: 2.4
Name: collabllm
Version: 0.0.8
Summary: (Oral @ ICML 2025) CollabLLM: From Passive Responders to Active Collaborators
Author-email: Shirley Wu <shirwu@stanford.edu>
License-Expression: MIT
Project-URL: Homepage, https://github.com/Wuyxin/collabllm
Project-URL: Issues, https://github.com/Wuyxin/collabllm/issues
Classifier: Programming Language :: Python :: 3
Classifier: Operating System :: OS Independent
Requires-Python: >=3.10
License-File: LICENSE
Requires-Dist: accelerate
Requires-Dist: bitsandbytes
Requires-Dist: datasets
Requires-Dist: huggingface-hub
Requires-Dist: litellm
Requires-Dist: nltk
Requires-Dist: numpy
Requires-Dist: openai
Requires-Dist: pandas
Requires-Dist: peft
Requires-Dist: python-dotenv
Requires-Dist: rich
Requires-Dist: scipy
Requires-Dist: tenacity
Requires-Dist: tiktoken
Requires-Dist: tokenizers
Requires-Dist: torch
Requires-Dist: tqdm
Requires-Dist: trl>0.18
Requires-Dist: transformers
Requires-Dist: vllm
Requires-Dist: wandb
Dynamic: license-file
